Metadata-Version: 2.1
Name: geodock
Version: 1.0.4
Author: Lee-Shin Chu
License: MIT
Requires-Python: >=3.7
License-File: LICENSE.md
Requires-Dist: torch >=2.0.1
Requires-Dist: pytorch-lightning >=1.8.6
Requires-Dist: einops >=0.6.0
Requires-Dist: biotite >=0.37.0
Requires-Dist: fair-esm >=2.0.0
